{
    "description": "",
    "tags": [],
    "size": {
        "height": 422,
        "width": 750
    },
    "objects": [
        {
            "id": 76950677,
            "classId": 6488528,
            "description": "",
            "geometryType": "rectangle",
            "labelerLogin": "inbox@datasetninja.com",
            "createdAt": "2023-10-23T17:58:46.588Z",
            "updatedAt": "2023-10-23T17:58:46.588Z",
            "tags": [],
            "classTitle": "drone",
            "points": {
                "exterior": [
                    [
                        262,
                        42
                    ],
                    [
                        725,
                        274
                    ]
                ],
                "interior": []
            }
        }
    ]
}